synaptogram/__init__.py
synaptogram/config.py
synaptogram/gui.enaml
synaptogram/instructions.html
synaptogram/main.py
synaptogram/model.py
synaptogram/presenter.py
synaptogram/reader.py
synaptogram/version.py
synaptogram/icons/__init__.py
synaptogram/icons/main-icon.ico
synaptogram/icons/main-icon.png
synaptogram/icons/make_icons.py
synaptogram-0.0.11.dist-info/METADATA
synaptogram-0.0.11.dist-info/WHEEL
synaptogram-0.0.11.dist-info/entry_points.txt
synaptogram-0.0.11.dist-info/top_level.txt
synaptogram-0.0.11.dist-info/RECORD
