Metadata-Version: 2.4
Name: synaptogram
Version: 0.0.11
Summary: Module for helping assess synapse counts
Author-email: Brad Buran <buran@ohsu.edu>
Maintainer-email: Brad Buran <buran@ohsu.edu>
Requires-Python: >=3.7
Requires-Dist: ndimage-enaml>=0.0.11
Requires-Dist: atom
Requires-Dist: enaml[qt6-pyside]
Requires-Dist: matplotlib
Requires-Dist: numpy<2.0
Requires-Dist: pandas
Requires-Dist: h5py
Provides-Extra: dev
Requires-Dist: docutils; extra == "dev"
